[{"项目ID": 10558, "项目名称": "2018 SNH48-孙芮应援会日常应援4.0", "项目链接": "https://zhongchou.modian.com/item/10558.html", "目标金额": 33333.0, "当前金额": 3913.33, "支持人数": 68}, {"user_id": 1558863, "nickname": "小傻几33", "pay_time": "2018-01-31 09:48:21", "backer_money": 3.33}, {"user_id": 1077603, "nickname": "水陌菁菁", "pay_time": "2018-01-31 00:35:53", "backer_money": 10}, {"user_id": 1522199, "nickname": "叁号客栈", "pay_time": "2018-01-30 13:11:56", "backer_money": 5}, {"user_id": 1558863, "nickname": "小傻几33", "pay_time": "2018-01-30 10:50:05", "backer_money": 1.12}, {"user_id": 1283593, "nickname": "寐妤丶", "pay_time": "2018-01-30 09:27:59", "backer_money": 5}, {"user_id": 1282186, "nickname": "3哥的2B粉条儿", "pay_time": "2018-01-30 01:25:29", "backer_money": 64.28}, {"user_id": 1077603, "nickname": "水陌菁菁", "pay_time": "2018-01-30 00:32:54", "backer_money": 10}, {"user_id": 1283593, "nickname": "寐妤丶", "pay_time": "2018-01-29 14:09:42", "backer_money": 5}, {"user_id": 1522199, "nickname": "叁号客栈", "pay_time": "2018-01-29 00:28:40", "backer_money": 1.3}, {"user_id": 1077603, "nickname": "水陌菁菁", "pay_time": "2018-01-29 00:26:46", "backer_money": 4.9}, {"user_id": 1283593, "nickname": "寐妤丶", "pay_time": "2018-01-28 14:52:04", "backer_money": 5}, {"user_id": 1077603, "nickname": "水陌菁菁", "pay_time": "2018-01-28 07:20:26", "backer_money": 10}, {"user_id": 1106567, "nickname": "女帝de胖次", "pay_time": "2018-01-27 14:51:34", "backer_money": 10}, {"user_id": 1283593, "nickname": "寐妤丶", "pay_time": "2018-01-27 14:45:08", "backer_money": 5}, {"user_id": 1077603, "nickname": "水陌菁菁", "pay_time": "2018-01-27 03:40:31", "backer_money": 10}, {"user_id": 1573628, "nickname": "一夜流火龙果", "pay_time": "2018-01-26 12:08:11", "backer_money": 10}, {"user_id": 1558863, "nickname": "小傻几33", "pay_time": "2018-01-26 10:41:24", "backer_money": 3.33}, {"user_id": 1558863, "nickname": "小傻几33", "pay_time": "2018-01-26 10:42:21", "backer_money": 1}, {"user_id": 1283593, "nickname": "寐妤丶", "pay_time": "2018-01-26 10:07:59", "backer_money": 5}, {"user_id": 1186098, "nickname": "KVN22", "pay_time": "2018-01-26 07:03:44", "backer_money": 34.08}, {"user_id": 1077603, "nickname": "水陌菁菁", "pay_time": "2018-01-26 00:41:53", "backer_money": 10}, {"user_id": 1282186, "nickname": "3哥的2B粉条儿", "pay_time": "2018-01-25 21:53:52", "backer_money": 11.11}, {"user_id": 1525221, "nickname": "虚伪瘦子atHurricane", "pay_time": "2018-01-25 15:15:46", "backer_money": 100}, {"user_id": 1522199, "nickname": "叁号客栈", "pay_time": "2018-01-25 14:02:49", "backer_money": 5}, {"user_id": 1182999, "nickname": "Sonn", "pay_time": "2018-01-25 13:25:10", "backer_money": 3.33}, {"user_id": 1283593, "nickname": "寐妤丶", "pay_time": "2018-01-25 09:09:21", "backer_money": 5}, {"user_id": 1077603, "nickname": "水陌菁菁", "pay_time": "2018-01-25 00:48:40", "backer_money": 10}, {"user_id": 1106567, "nickname": "女帝de胖次", "pay_time": "2018-01-24 16:37:25", "backer_money": 10}, {"user_id": 1282186, "nickname": "3哥的2B粉条儿", "pay_time": "2018-01-24 14:37:18", "backer_money": 10.55}, {"user_id": 1558863, "nickname": "小傻几33", "pay_time": "2018-01-24 09:41:43", "backer_money": 2}, {"user_id": 1283593, "nickname": "寐妤丶", "pay_time": "2018-01-24 09:04:20", "backer_money": 5}, {"user_id": 1077603, "nickname": "水陌菁菁", "pay_time": "2018-01-24 05:36:07", "backer_money": 5}, {"user_id": 1558863, "nickname": "小傻几33", "pay_time": "2018-01-23 15:37:05", "backer_money": 2}, {"user_id": 1283593, "nickname": "寐妤丶", "pay_time": "2018-01-23 09:49:11", "backer_money": 5}, {"user_id": 1077603, "nickname": "水陌菁菁", "pay_time": "2018-01-23 03:40:54", "backer_money": 5}, {"user_id": 1351602, "nickname": "JustLyu", "pay_time": "2018-01-22 17:02:07", "backer_money": 50}, {"user_id": 1283593, "nickname": "寐妤丶", "pay_time": "2018-01-22 11:44:33", "backer_money": 5}, {"user_id": 1077603, "nickname": "水陌菁菁", "pay_time": "2018-01-22 04:11:21", "backer_money": 5}, {"user_id": 1283593, "nickname": "寐妤丶", "pay_time": "2018-01-21 14:47:09", "backer_money": 10}, {"user_id": 1558863, "nickname": "小傻几33", "pay_time": "2018-01-21 12:01:13", "backer_money": 1}, {"user_id": 1186098, "nickname": "KVN22", "pay_time": "2018-01-21 06:50:44", "backer_money": 9}, {"user_id": 1077603, "nickname": "水陌菁菁", "pay_time": "2018-01-21 00:32:30", "backer_money": 5}, {"user_id": 1283593, "nickname": "寐妤丶", "pay_time": "2018-01-20 10:14:29", "backer_money": 10}, {"user_id": 1077603, "nickname": "水陌菁菁", "pay_time": "2018-01-20 03:23:03", "backer_money": 10}, {"user_id": 1283593, "nickname": "寐妤丶", "pay_time": "2018-01-19 14:49:25", "backer_money": 10}, {"user_id": 1558863, "nickname": "小傻几33", "pay_time": "2018-01-19 11:49:42", "backer_money": 1}, {"user_id": 1077603, "nickname": "水陌菁菁", "pay_time": "2018-01-19 00:21:45", "backer_money": 5}, {"user_id": 1186098, "nickname": "KVN22", "pay_time": "2018-01-18 23:35:29", "backer_money": 35.17}, {"user_id": 1558863, "nickname": "小傻几33", "pay_time": "2018-01-18 18:17:23", "backer_money": 1}, {"user_id": 1575044, "nickname": "焰酱焰酱焰酱", "pay_time": "2018-01-18 15:23:58", "backer_money": 3.5}, {"user_id": 1283593, "nickname": "寐妤丶", "pay_time": "2018-01-18 10:15:04", "backer_money": 10}, {"user_id": 1503921, "nickname": "扎个小Jo", "pay_time": "2018-01-18 01:24:55", "backer_money": 12}, {"user_id": 1077603, "nickname": "水陌菁菁", "pay_time": "2018-01-18 01:21:58", "backer_money": 5}, {"user_id": 1282186, "nickname": "3哥的2B粉条儿", "pay_time": "2018-01-17 20:39:33", "backer_money": 19}, {"user_id": 1106567, "nickname": "女帝de胖次", "pay_time": "2018-01-17 20:36:59", "backer_money": 10}, {"user_id": 1182999, "nickname": "Sonn", "pay_time": "2018-01-17 12:37:55", "backer_money": 3.33}, {"user_id": 1558863, "nickname": "小傻几33", "pay_time": "2018-01-17 11:52:12", "backer_money": 1}, {"user_id": 1329045, "nickname": "又萌又软啦啦啦", "pay_time": "2018-01-17 10:01:21", "backer_money": 10}, {"user_id": 1283593, "nickname": "寐妤丶", "pay_time": "2018-01-17 08:32:49", "backer_money": 10}, {"user_id": 1077603, "nickname": "水陌菁菁", "pay_time": "2018-01-17 01:13:18", "backer_money": 10}, {"user_id": 1503921, "nickname": "扎个小Jo", "pay_time": "2018-01-17 00:56:42", "backer_money": 12.34}, {"user_id": 1447967, "nickname": "像一具尸体", "pay_time": "2018-01-16 16:32:42", "backer_money": 1}, {"user_id": 1282186, "nickname": "3哥的2B粉条儿", "pay_time": "2018-01-16 16:27:20", "backer_money": 20}, {"user_id": 1079932, "nickname": "孙芮极速前进", "pay_time": "2018-01-16 13:01:28", "backer_money": 3.33}, {"user_id": 1282186, "nickname": "3哥的2B粉条儿", "pay_time": "2018-01-16 11:32:03", "backer_money": 20.03}, {"user_id": 1283593, "nickname": "寐妤丶", "pay_time": "2018-01-16 08:22:39", "backer_money": 10}, {"user_id": 1182999, "nickname": "Sonn", "pay_time": "2018-01-16 07:26:30", "backer_money": 3.3}, {"user_id": 1186098, "nickname": "KVN22", "pay_time": "2018-01-16 06:57:24", "backer_money": 10}, {"user_id": 1503921, "nickname": "扎个小Jo", "pay_time": "2018-01-16 02:11:52", "backer_money": 3.29}, {"user_id": 1558863, "nickname": "小傻几33", "pay_time": "2018-01-16 01:38:27", "backer_money": 10}, {"user_id": 1077603, "nickname": "水陌菁菁", "pay_time": "2018-01-16 00:24:42", "backer_money": 10}, {"user_id": 1558863, "nickname": "小傻几33", "pay_time": "2018-01-15 22:42:51", "backer_money": 1}, {"user_id": 1549628, "nickname": "十八家少国公", "pay_time": "2018-01-15 15:03:44", "backer_money": 50}, {"user_id": 1283593, "nickname": "寐妤丶", "pay_time": "2018-01-15 14:56:30", "backer_money": 10}, {"user_id": 1522199, "nickname": "叁号客栈", "pay_time": "2018-01-15 14:17:56", "backer_money": 2.71}, {"user_id": 1503921, "nickname": "扎个小Jo", "pay_time": "2018-01-15 01:51:33", "backer_money": 3.01}, {"user_id": 1282186, "nickname": "3哥的2B粉条儿", "pay_time": "2018-01-15 00:54:04", "backer_money": 39.99}, {"user_id": 1077603, "nickname": "水陌菁菁", "pay_time": "2018-01-15 00:17:49", "backer_money": 10}, {"user_id": 1186098, "nickname": "KVN22", "pay_time": "2018-01-14 22:29:17", "backer_money": 5.34}, {"user_id": 1585141, "nickname": "LucilleHuntington", "pay_time": "2018-01-14 19:50:47", "backer_money": 5}, {"user_id": 1106567, "nickname": "女帝de胖次", "pay_time": "2018-01-14 15:54:33", "backer_money": 6.66}, {"user_id": 1503921, "nickname": "扎个小Jo", "pay_time": "2018-01-14 14:45:40", "backer_money": 1}, {"user_id": 1503921, "nickname": "扎个小Jo", "pay_time": "2018-01-14 14:45:08", "backer_money": 11}, {"user_id": 1584815, "nickname": "我家小二Simone", "pay_time": "2018-01-14 11:46:08", "backer_money": 10}, {"user_id": 1558863, "nickname": "小傻几33", "pay_time": "2018-01-14 10:09:59", "backer_money": 1}, {"user_id": 1283593, "nickname": "寐妤丶", "pay_time": "2018-01-14 08:54:16", "backer_money": 10}, {"user_id": 1506633, "nickname": "Bury.記忆", "pay_time": "2018-01-14 08:16:27", "backer_money": 66}, {"user_id": 1077603, "nickname": "水陌菁菁", "pay_time": "2018-01-14 01:52:35", "backer_money": 33}, {"user_id": 1516526, "nickname": "虔瑾。", "pay_time": "2018-01-14 00:34:31", "backer_money": 1}, {"user_id": 1282186, "nickname": "3哥的2B粉条儿", "pay_time": "2018-01-14 00:27:41", "backer_money": 20.49}, {"user_id": 1522199, "nickname": "叁号客栈", "pay_time": "2018-01-14 00:06:58", "backer_money": 7.29}, {"user_id": 1498956, "nickname": "M", "pay_time": "2018-01-13 23:25:03", "backer_money": 50}, {"user_id": 1282186, "nickname": "3哥的2B粉条儿", "pay_time": "2018-01-13 23:17:35", "backer_money": 12.22}, {"user_id": 1186098, "nickname": "KVN22", "pay_time": "2018-01-13 22:43:39", "backer_money": 10}, {"user_id": 1558863, "nickname": "小傻几33", "pay_time": "2018-01-13 17:50:25", "backer_money": 10}, {"user_id": 1283593, "nickname": "寐妤丶", "pay_time": "2018-01-13 12:08:04", "backer_money": 10}, {"user_id": 1283717, "nickname": "三白__", "pay_time": "2018-01-13 01:20:49", "backer_money": 10}, {"user_id": 1503921, "nickname": "扎个小Jo", "pay_time": "2018-01-13 01:20:01", "backer_money": 11.6}, {"user_id": 1283717, "nickname": "三白__", "pay_time": "2018-01-13 01:19:27", "backer_money": 10}, {"user_id": 1077603, "nickname": "水陌菁菁", "pay_time": "2018-01-13 01:16:59", "backer_money": 33}, {"user_id": 1283717, "nickname": "三白__", "pay_time": "2018-01-13 01:15:43", "backer_money": 10}, {"user_id": 1522199, "nickname": "叁号客栈", "pay_time": "2018-01-12 22:06:46", "backer_money": 5.4}, {"user_id": 1186098, "nickname": "KVN22", "pay_time": "2018-01-12 19:51:24", "backer_money": 33.37}, {"user_id": 1067879, "nickname": "尼古拉斯知秋", "pay_time": "2018-01-12 16:41:58", "backer_money": 10}, {"user_id": 1526790, "nickname": "喜阳阳羊羊", "pay_time": "2018-01-12 16:34:04", "backer_money": 50}, {"user_id": 1504767, "nickname": "i非游戏", "pay_time": "2018-01-12 16:26:49", "backer_money": 3.33}, {"user_id": 1515909, "nickname": "大L", "pay_time": "2018-01-12 13:37:43", "backer_money": 13.3}, {"user_id": 1500725, "nickname": "只给孙芮过夏天的鱼食", "pay_time": "2018-01-12 13:27:09", "backer_money": 10}, {"user_id": 1503921, "nickname": "扎个小Jo", "pay_time": "2018-01-12 13:21:57", "backer_money": 10}, {"user_id": 1283593, "nickname": "寐妤丶", "pay_time": "2018-01-12 08:28:42", "backer_money": 10}, {"user_id": 1558863, "nickname": "小傻几33", "pay_time": "2018-01-12 01:04:02", "backer_money": 10}, {"user_id": 1077603, "nickname": "水陌菁菁", "pay_time": "2018-01-12 00:58:13", "backer_money": 10}, {"user_id": 1186098, "nickname": "KVN22", "pay_time": "2018-01-12 00:12:44", "backer_money": 4.2}, {"user_id": 1577443, "nickname": "李小林啊", "pay_time": "2018-01-11 23:53:46", "backer_money": 10}, {"user_id": 1077603, "nickname": "水陌菁菁", "pay_time": "2018-01-11 19:07:42", "backer_money": 5.8}, {"user_id": 1282186, "nickname": "3哥的2B粉条儿", "pay_time": "2018-01-11 13:09:55", "backer_money": 10}, {"user_id": 1283593, "nickname": "寐妤丶", "pay_time": "2018-01-11 09:02:35", "backer_money": 10}, {"user_id": 1503921, "nickname": "扎个小Jo", "pay_time": "2018-01-11 02:07:56", "backer_money": 16.7}, {"user_id": 1558863, "nickname": "小傻几33", "pay_time": "2018-01-11 01:59:09", "backer_money": 10}, {"user_id": 1077603, "nickname": "水陌菁菁", "pay_time": "2018-01-11 00:34:34", "backer_money": 10}, {"user_id": 1522199, "nickname": "叁号客栈", "pay_time": "2018-01-10 22:51:32", "backer_money": 3.3}, {"user_id": 1309279, "nickname": "暗恋火箭筒", "pay_time": "2018-01-10 21:18:59", "backer_money": 10}, {"user_id": 1186098, "nickname": "KVN22", "pay_time": "2018-01-10 21:14:02", "backer_money": 34.67}, {"user_id": 1503921, "nickname": "扎个小Jo", "pay_time": "2018-01-10 18:17:23", "backer_money": 10}, {"user_id": 1126869, "nickname": "另请高明", "pay_time": "2018-01-10 09:16:54", "backer_money": 2}, {"user_id": 1283593, "nickname": "寐妤丶", "pay_time": "2018-01-10 09:15:21", "backer_money": 10}, {"user_id": 1077603, "nickname": "水陌菁菁", "pay_time": "2018-01-10 05:47:26", "backer_money": 50}, {"user_id": 1558863, "nickname": "小傻几33", "pay_time": "2018-01-10 01:01:45", "backer_money": 10}, {"user_id": 1282186, "nickname": "3哥的2B粉条儿", "pay_time": "2018-01-10 00:08:22", "backer_money": 23.33}, {"user_id": 1522199, "nickname": "叁号客栈", "pay_time": "2018-01-09 23:55:36", "backer_money": 3.34}, {"user_id": 1106567, "nickname": "女帝de胖次", "pay_time": "2018-01-09 19:45:09", "backer_money": 6.66}, {"user_id": 1186098, "nickname": "KVN22", "pay_time": "2018-01-09 19:28:57", "backer_money": 2.67}, {"user_id": 1077603, "nickname": "水陌菁菁", "pay_time": "2018-01-09 15:16:01", "backer_money": 10}, {"user_id": 1550191, "nickname": "小八_", "pay_time": "2018-01-09 14:12:13", "backer_money": 1}, {"user_id": 1078670, "nickname": "逸可赛艇孙三三", "pay_time": "2018-01-09 13:11:11", "backer_money": 2.33}, {"user_id": 1078670, "nickname": "逸可赛艇孙三三", "pay_time": "2018-01-09 13:09:59", "backer_money": 1}, {"user_id": 1510103, "nickname": "奇異果_", "pay_time": "2018-01-09 13:07:45", "backer_money": 33}, {"user_id": 1562571, "nickname": "怀中猫♡", "pay_time": "2018-01-09 13:05:44", "backer_money": 1}, {"user_id": 1514228, "nickname": "白永泽", "pay_time": "2018-01-09 12:59:46", "backer_money": 1}, {"user_id": 1037863, "nickname": "熟悉的陌生人", "pay_time": "2018-01-09 12:57:26", "backer_money": 5}, {"user_id": 1037863, "nickname": "熟悉的陌生人", "pay_time": "2018-01-09 12:55:28", "backer_money": 1}, {"user_id": 1202111, "nickname": "SR五选选拔", "pay_time": "2018-01-09 12:19:37", "backer_money": 5}, {"user_id": 1463628, "nickname": "不存于世间的富江", "pay_time": "2018-01-09 09:37:13", "backer_money": 5}, {"user_id": 1283593, "nickname": "寐妤丶", "pay_time": "2018-01-09 09:32:15", "backer_money": 10}, {"user_id": 1282186, "nickname": "3哥的2B粉条儿", "pay_time": "2018-01-09 01:39:24", "backer_money": 68.7}, {"user_id": 1503921, "nickname": "扎个小Jo", "pay_time": "2018-01-09 00:58:31", "backer_money": 3.3}, {"user_id": 1503921, "nickname": "扎个小Jo", "pay_time": "2018-01-09 00:57:58", "backer_money": 10}, {"user_id": 1558863, "nickname": "小傻几33", "pay_time": "2018-01-09 00:56:03", "backer_money": 10}, {"user_id": 1077603, "nickname": "水陌菁菁", "pay_time": "2018-01-09 00:39:30", "backer_money": 10}, {"user_id": 1106567, "nickname": "女帝de胖次", "pay_time": "2018-01-08 22:37:56", "backer_money": 10}, {"user_id": 1577443, "nickname": "李小林啊", "pay_time": "2018-01-08 20:52:37", "backer_money": 10}, {"user_id": 1186098, "nickname": "KVN22", "pay_time": "2018-01-08 20:11:35", "backer_money": 52.67}, {"user_id": 1576822, "nickname": "KylinS", "pay_time": "2018-01-08 10:54:58", "backer_money": 33}, {"user_id": 1550191, "nickname": "小八_", "pay_time": "2018-01-08 10:28:20", "backer_money": 1}, {"user_id": 1283593, "nickname": "寐妤丶", "pay_time": "2018-01-08 09:47:30", "backer_money": 10}, {"user_id": 1504767, "nickname": "i非游戏", "pay_time": "2018-01-08 09:38:15", "backer_money": 3.33}, {"user_id": 1503921, "nickname": "扎个小Jo", "pay_time": "2018-01-08 02:57:09", "backer_money": 37.67}, {"user_id": 1282186, "nickname": "3哥的2B粉条儿", "pay_time": "2018-01-08 02:18:25", "backer_money": 10}, {"user_id": 1077603, "nickname": "水陌菁菁", "pay_time": "2018-01-08 01:41:26", "backer_money": 10}, {"user_id": 1522199, "nickname": "叁号客栈", "pay_time": "2018-01-08 00:23:20", "backer_money": 1.33}, {"user_id": 1558863, "nickname": "小傻几33", "pay_time": "2018-01-08 00:20:32", "backer_money": 10}, {"user_id": 1577443, "nickname": "李小林啊", "pay_time": "2018-01-07 21:16:48", "backer_money": 10}, {"user_id": 1283593, "nickname": "寐妤丶", "pay_time": "2018-01-07 16:11:01", "backer_money": 10}, {"user_id": 1550191, "nickname": "小八_", "pay_time": "2018-01-07 08:24:49", "backer_money": 1}, {"user_id": 1558863, "nickname": "小傻几33", "pay_time": "2018-01-07 08:01:20", "backer_money": 10}, {"user_id": 1186098, "nickname": "KVN22", "pay_time": "2018-01-07 07:44:45", "backer_money": 22}, {"user_id": 1077603, "nickname": "水陌菁菁", "pay_time": "2018-01-07 02:26:15", "backer_money": 10}, {"user_id": 1351602, "nickname": "JustLyu", "pay_time": "2018-01-06 23:25:33", "backer_money": 5}, {"user_id": 1577443, "nickname": "李小林啊", "pay_time": "2018-01-06 19:44:15", "backer_money": 10}, {"user_id": 1524230, "nickname": "L   J   Y", "pay_time": "2018-01-06 18:15:00", "backer_money": 3}, {"user_id": 1186098, "nickname": "KVN22", "pay_time": "2018-01-06 17:56:12", "backer_money": 21.6}, {"user_id": 1580494, "nickname": "苏虾", "pay_time": "2018-01-06 17:47:45", "backer_money": 3.33}, {"user_id": 1522199, "nickname": "叁号客栈", "pay_time": "2018-01-06 17:08:39", "backer_money": 3.33}, {"user_id": 1550191, "nickname": "小八_", "pay_time": "2018-01-06 09:23:14", "backer_money": 1}, {"user_id": 1077603, "nickname": "水陌菁菁", "pay_time": "2018-01-06 02:04:10", "backer_money": 10}, {"user_id": 1282186, "nickname": "3哥的2B粉条儿", "pay_time": "2018-01-06 01:42:13", "backer_money": 10}, {"user_id": 1283593, "nickname": "寐妤丶", "pay_time": "2018-01-06 00:10:09", "backer_money": 10}, {"user_id": 1558863, "nickname": "小傻几33", "pay_time": "2018-01-06 00:07:53", "backer_money": 10}, {"user_id": 1106567, "nickname": "女帝de胖次", "pay_time": "2018-01-05 15:36:09", "backer_money": 6.44}, {"user_id": 1094775, "nickname": "姬小路秋子", "pay_time": "2018-01-05 15:09:46", "backer_money": 100}, {"user_id": 1522199, "nickname": "叁号客栈", "pay_time": "2018-01-05 12:59:44", "backer_money": 3.3}, {"user_id": 1514493, "nickname": "OHO涼白開", "pay_time": "2018-01-05 09:50:50", "backer_money": 50}, {"user_id": 1283593, "nickname": "寐妤丶", "pay_time": "2018-01-05 09:41:14", "backer_money": 10}, {"user_id": 1550191, "nickname": "小八_", "pay_time": "2018-01-05 08:56:16", "backer_money": 1}, {"user_id": 1577443, "nickname": "李小林啊", "pay_time": "2018-01-05 08:44:56", "backer_money": 10}, {"user_id": 1186098, "nickname": "KVN22", "pay_time": "2018-01-05 06:53:36", "backer_money": 61.67}, {"user_id": 1077603, "nickname": "水陌菁菁", "pay_time": "2018-01-05 02:15:12", "backer_money": 10}, {"user_id": 1558863, "nickname": "小傻几33", "pay_time": "2018-01-05 00:05:01", "backer_money": 10}, {"user_id": 1106567, "nickname": "女帝de胖次", "pay_time": "2018-01-04 20:49:14", "backer_money": 10}, {"user_id": 1550191, "nickname": "小八_", "pay_time": "2018-01-04 19:17:35", "backer_money": 1}, {"user_id": 1347921, "nickname": "carefree", "pay_time": "2018-01-04 19:04:30", "backer_money": 1}, {"user_id": 1092855, "nickname": "叫Terry的田小于", "pay_time": "2018-01-04 14:00:39", "backer_money": 33}, {"user_id": 1516138, "nickname": "Gravity", "pay_time": "2018-01-04 13:49:04", "backer_money": 3.33}, {"user_id": 1522199, "nickname": "叁号客栈", "pay_time": "2018-01-04 13:44:54", "backer_money": 10}, {"user_id": 1371430, "nickname": "大哥家的二狗", "pay_time": "2018-01-04 13:44:17", "backer_money": 4}, {"user_id": 1510103, "nickname": "奇異果_", "pay_time": "2018-01-04 13:39:40", "backer_money": 33}, {"user_id": 1576656, "nickname": "Prisoner", "pay_time": "2018-01-04 12:03:18", "backer_money": 3}, {"user_id": 1088187, "nickname": "美好的夜晚开始了_躁起来", "pay_time": "2018-01-04 11:51:11", "backer_money": 100}, {"user_id": 1349739, "nickname": "徐多斤_", "pay_time": "2018-01-04 11:34:35", "backer_money": 10}, {"user_id": 1283593, "nickname": "寐妤丶", "pay_time": "2018-01-04 09:55:33", "backer_money": 10}, {"user_id": 1186098, "nickname": "KVN22", "pay_time": "2018-01-04 06:51:20", "backer_money": 33.56}, {"user_id": 1558863, "nickname": "小傻几33", "pay_time": "2018-01-04 02:36:38", "backer_money": 10}, {"user_id": 1077603, "nickname": "水陌菁菁", "pay_time": "2018-01-04 00:28:29", "backer_money": 10}, {"user_id": 1282186, "nickname": "3哥的2B粉条儿", "pay_time": "2018-01-03 23:12:05", "backer_money": 50}, {"user_id": 1351602, "nickname": "JustLyu", "pay_time": "2018-01-03 21:58:48", "backer_money": 5}, {"user_id": 1106567, "nickname": "女帝de胖次", "pay_time": "2018-01-03 14:02:18", "backer_money": 10.02}, {"user_id": 1576391, "nickname": "首推芮哥的小思思儿", "pay_time": "2018-01-03 13:40:09", "backer_money": 10}, {"user_id": 1576391, "nickname": "首推芮哥的小思思儿", "pay_time": "2018-01-03 13:34:57", "backer_money": 2}, {"user_id": 1283593, "nickname": "寐妤丶", "pay_time": "2018-01-03 11:01:47", "backer_money": 10}, {"user_id": 1550191, "nickname": "小八_", "pay_time": "2018-01-03 07:42:34", "backer_money": 1}, {"user_id": 1186098, "nickname": "KVN22", "pay_time": "2018-01-03 06:48:55", "backer_money": 14.66}, {"user_id": 1077603, "nickname": "水陌菁菁", "pay_time": "2018-01-03 00:45:40", "backer_money": 10}, {"user_id": 1558863, "nickname": "小傻几33", "pay_time": "2018-01-03 00:34:40", "backer_money": 10}, {"user_id": 1106567, "nickname": "女帝de胖次", "pay_time": "2018-01-02 20:24:50", "backer_money": 23.33}, {"user_id": 1510103, "nickname": "奇異果_", "pay_time": "2018-01-02 13:05:42", "backer_money": 10}, {"user_id": 1283905, "nickname": "阿澄啊", "pay_time": "2018-01-02 12:58:27", "backer_money": 2.37}, {"user_id": 1550191, "nickname": "小八_", "pay_time": "2018-01-02 11:53:29", "backer_money": 1}, {"user_id": 1283593, "nickname": "寐妤丶", "pay_time": "2018-01-02 11:05:09", "backer_money": 10}, {"user_id": 1335533, "nickname": "林允儿的迷弟", "pay_time": "2018-01-02 10:01:13", "backer_money": 7.5}, {"user_id": 1558863, "nickname": "小傻几33", "pay_time": "2018-01-02 09:35:46", "backer_money": 10}, {"user_id": 1576870, "nickname": "望明月", "pay_time": "2018-01-02 09:35:50", "backer_money": 10}, {"user_id": 1329045, "nickname": "又萌又软啦啦啦", "pay_time": "2018-01-02 09:14:33", "backer_money": 10}, {"user_id": 1351602, "nickname": "JustLyu", "pay_time": "2018-01-02 08:54:35", "backer_money": 10}, {"user_id": 1077603, "nickname": "水陌菁菁", "pay_time": "2018-01-02 07:04:37", "backer_money": 10}, {"user_id": 1186098, "nickname": "KVN22", "pay_time": "2018-01-02 07:01:02", "backer_money": 33}, {"user_id": 1573628, "nickname": "一夜流火龙果", "pay_time": "2018-01-01 23:18:31", "backer_money": 10}, {"user_id": 1100787, "nickname": "歪提", "pay_time": "2018-01-01 21:58:18", "backer_money": 81.36}, {"user_id": 1125036, "nickname": "注意身体", "pay_time": "2018-01-01 21:27:11", "backer_money": 10}, {"user_id": 1576656, "nickname": "Prisoner", "pay_time": "2018-01-01 20:49:30", "backer_money": 10}, {"user_id": 1576656, "nickname": "Prisoner", "pay_time": "2018-01-01 20:48:21", "backer_money": 7.2}, {"user_id": 1576641, "nickname": "娜爱芹", "pay_time": "2018-01-01 20:19:28", "backer_money": 10}, {"user_id": 1506633, "nickname": "Bury.記忆", "pay_time": "2018-01-01 18:47:43", "backer_money": 33}, {"user_id": 1424390, "nickname": "芮宝的小虎牙", "pay_time": "2018-01-01 17:47:49", "backer_money": 10}, {"user_id": 1466744, "nickname": "너는 태양", "pay_time": "2018-01-01 16:52:23", "backer_money": 15}, {"user_id": 1186098, "nickname": "KVN22", "pay_time": "2018-01-01 16:40:06", "backer_money": 102.34}, {"user_id": 1576391, "nickname": "首推芮哥的小思思儿", "pay_time": "2018-01-01 15:12:28", "backer_money": 3}, {"user_id": 1576391, "nickname": "首推芮哥的小思思儿", "pay_time": "2018-01-01 15:11:53", "backer_money": 1}, {"user_id": 1446275, "nickname": "MoMaek芮", "pay_time": "2018-01-01 15:04:57", "backer_money": 10}, {"user_id": 1536051, "nickname": "四外手机", "pay_time": "2018-01-01 15:02:28", "backer_money": 33}, {"user_id": 1088187, "nickname": "美好的夜晚开始了_躁起来", "pay_time": "2018-01-01 13:57:29", "backer_money": 100}, {"user_id": 1350326, "nickname": "陆纸帅的飞起", "pay_time": "2018-01-01 13:53:37", "backer_money": 1}, {"user_id": 1515909, "nickname": "大L", "pay_time": "2018-01-01 13:22:08", "backer_money": 33}, {"user_id": 1341566, "nickname": "孙芮最好看", "pay_time": "2018-01-01 12:55:28", "backer_money": 33}, {"user_id": 1077603, "nickname": "水陌菁菁", "pay_time": "2018-01-01 12:54:40", "backer_money": 50}, {"user_id": 1088792, "nickname": "Tifrinygid", "pay_time": "2018-01-01 12:53:41", "backer_money": 33}, {"user_id": 1106567, "nickname": "女帝de胖次", "pay_time": "2018-01-01 12:49:39", "backer_money": 66.66}, {"user_id": 1504767, "nickname": "i非游戏", "pay_time": "2018-01-01 12:43:57", "backer_money": 10}, {"user_id": 1550191, "nickname": "小八_", "pay_time": "2018-01-01 12:41:31", "backer_money": 10}, {"user_id": 1522199, "nickname": "叁号客栈", "pay_time": "2018-01-01 12:32:45", "backer_money": 10}, {"user_id": 1558863, "nickname": "小傻几33", "pay_time": "2018-01-01 12:25:19", "backer_money": 10}, {"user_id": 1446275, "nickname": "MoMaek芮", "pay_time": "2018-01-01 12:23:36", "backer_money": 10}, {"user_id": 1364403, "nickname": "拿两个煎饼走吧_", "pay_time": "2018-01-01 12:07:49", "backer_money": 8}, {"user_id": 1282186, "nickname": "3哥的2B粉条儿", "pay_time": "2018-01-01 12:08:00", "backer_money": 100}, {"user_id": 1562458, "nickname": "GO_HO", "pay_time": "2018-01-01 11:59:51", "backer_money": 33}, {"user_id": 1503921, "nickname": "扎个小Jo", "pay_time": "2018-01-01 11:58:15", "backer_money": 33}, {"user_id": 1181181, "nickname": "Dieuss時间", "pay_time": "2018-01-01 11:51:41", "backer_money": 10}, {"user_id": 1525221, "nickname": "虚伪瘦子atHurricane", "pay_time": "2018-01-01 11:51:19", "backer_money": 100}]
