[{"项目ID": 13705, "项目名称": "【SNH48】张昕第五届总选集资", "项目链接": "https://zhongchou.modian.com/item/13705.html", "目标金额": 10000.0, "当前金额": 64.69, "支持人数": 8}, {"user_id": 997171, "nickname": "_watermelonn_", "pay_time": "2018-04-07 00:14:14", "backer_money": 5.2}, {"user_id": 997171, "nickname": "_watermelonn_", "pay_time": "2018-04-06 00:51:49", "backer_money": 10}, {"user_id": 1436953, "nickname": "为偶像而奋斗", "pay_time": "2018-04-05 15:09:03", "backer_money": 6.11}, {"user_id": 1631737, "nickname": "对待叉雨要认真6", "pay_time": "2018-04-05 10:06:54", "backer_money": 10}, {"user_id": 1073933, "nickname": "时光名为有心", "pay_time": "2018-04-03 23:07:40", "backer_money": 10}, {"user_id": 1301473, "nickname": "输入昵称使用真实名字", "pay_time": "2018-04-03 15:54:14", "backer_money": 1}, {"user_id": 1684035, "nickname": "billjyc1_h4u", "pay_time": "2018-04-03 14:58:12", "backer_money": 10.19}, {"user_id": 1301473, "nickname": "输入昵称使用真实名字", "pay_time": "2018-04-02 16:45:04", "backer_money": 1}, {"user_id": 1494603, "nickname": "吾爱心中菡", "pay_time": "2018-04-02 14:22:44", "backer_money": 1}, {"user_id": 1510321, "nickname": "易夏", "pay_time": "2018-04-02 13:31:41", "backer_money": 10.19}]
